{
  "nick": "黒羽鳴鏑",
  "occupation": "天領奉行",
  "area": "Inazuma",
  "rare": "4",
  "weapon": "Bow",
  "element": "Electro",
  "constellation": "羽団扇座",
  "desc": "「天領奉行」の大将。果敢かつ勇猛である。",
  "birth": "07/14",
  "battle_talent": {
    "normal_name": "通常攻撃·天狗伝弓術",
    "normal_img": "kujou_sara_s1",
    "normal_desc1": "最大5段の連続射撃を行う。",
    "normal_desc2": "ダメージがより高く、より精確な狙い撃ちを発動する。照準時、雷霆の力が矢先に凝集する。雷霆の力に満ちた矢は、敵に雷元素ダメージを与える。「烏羽護持」状態の時、フルチャージを終えた矢は命中時に「烏羽」を残す。",
    "normal_desc3": "空中から矢の雨を放ち、凄まじいスピードで落下し地面に衝撃を与え、落下時に範囲ダメージを与える。",
    "element_name": "烏天狗雷霆召呪",
    "element_img": "kujou_sara_s2",
    "element_desc": "天狗の神速で後方へ移動し、烏羽の加護を呼びかける。<br>18秒間続く「烏羽護持」を獲得する。九条裟羅がフルチャージを終えた矢を放つと、「烏羽護持」を消費し、命中した位置に「烏羽」を残す。<br>「烏羽」は短時間後に天狗呪雷·伏を引き起こし、範囲内の敵に雷元素ダメージを与え、範囲内のフィールド上キャラクターの攻撃力を、九条裟羅の基礎攻撃力を基準にアップさせる。<br><br>各種天狗呪雷による攻撃力アップ効果は重ね掛けできず、効果と継続時間は最後に発動したものを基準とする。<br><br><i>天狗一族の中には、雷元素の神の目を獲得できる者は少なくない。それでも、彼らは雷元素を操る時、呪文を唱えて雷神に敬意を表す習慣がある。呪文はこのようなものだ、</i><br><i>「尊い鳴神大権現様よ、人々にご加護を、雷霆の力を。娑婆訶！」</i>",
    "final_name": "煌煌千道鎮式",
    "final_img": "kujou_sara_s3",
    "final_desc": "目標位置に天狗呪雷·金剛破を下し、雷元素範囲ダメージを与える。その後、天狗呪雷·金剛破は4つの連続する天狗呪雷·雷礫に分裂し、雷元素範囲ダメージを与える。\n天狗呪雷·金剛破と天狗呪雷·雷礫は、範囲内のフィールド上キャラクターに、元素スキル「烏天狗雷霆召呪」に相当する攻撃力アップ効果を与える。<br><br>各種天狗呪雷による攻撃力アップ効果は重ね掛けできず、効果と継続時間は最後に発動したものを基準とする。<br><br><i>九条裟羅は天狗に背を向け、天領奉行への信仰を一時的に失っていた。戸惑いを打ち破った彼女にとって、これこそが彼女が新たに見つけた、自分自身の雷光であった。</i>"
  },
  "basic_talent": {
    "talent2_name": "検地",
    "talent2_img": "kujou_sara_p2",
    "talent2_desc": "稲妻の探索任務の所要時間-25%。",
    "talent3_name": "不動心",
    "talent3_img": "kujou_sara_p3",
    "talent3_desc": "烏天狗雷霆召呪による「烏羽護持」の時、狙い撃ちのチャージ時間-60%。",
    "talent1_name": "御公儀",
    "talent1_img": "kujou_sara_p1",
    "talent1_desc": "天狗呪雷·伏は敵に命中すると、九条裟羅の元素チャージ効率を基準にし、その100%の元素チャージ効率毎に、チーム全員の元素エネルギーを1.2回復する。この効果は3秒毎に1回のみ発動可能。"
  },
  "sof": {
    "sof1_name": "烏目",
    "sof1_img": "kujou_sara_c1",
    "sof1_desc": "天狗呪雷がキャラクターに攻撃力アップ効果を付与、または敵に命中すると、烏天狗雷霆召呪のクールタイム-1秒。\nこの効果は3秒毎に1回のみ発動可能。",
    "sof2_name": "鴉の羽",
    "sof2_img": "kujou_sara_c2",
    "sof2_desc": "烏天狗雷霆召呪を発動した時、九条裟羅が元々いた位置に微弱な天狗呪雷·伏の「烏羽」を発動し、本来の30%のダメージを与える。",
    "sof3_name": "心魔",
    "sof3_img": "kujou_sara_c3",
    "sof3_desc": "煌煌千道鎮式のスキルLv.+3。\n最大Lv.15まで。",
    "sof4_name": "徹証",
    "sof4_img": "kujou_sara_c4",
    "sof4_desc": "煌煌千道鎮式による天狗呪雷·雷礫の数が6つに増加する。",
    "sof5_name": "呪詠",
    "sof5_img": "kujou_sara_c5",
    "sof5_desc": "烏天狗雷霆召呪のスキルLv.+3。\n最大Lv.15まで。",
    "sof6_name": "我界",
    "sof6_img": "kujou_sara_c6",
    "sof6_desc": "天狗呪雷による攻撃力アップ状態のキャラクターは、雷元素ダメージの会心ダメージ+60%。"
  }
}